acled/__init__.py
acled/_version.py
acled/config.py
acled/exceptions.py
acled/log.py
acled/cli/__init__.py
acled/cli/main.py
acled/cli/commands/__init__.py
acled/cli/commands/auth.py
acled/cli/commands/base.py
acled/cli/commands/data.py
acled/cli/formatters/__init__.py
acled/cli/formatters/base.py
acled/cli/formatters/csv.py
acled/cli/formatters/json.py
acled/cli/formatters/summary.py
acled/cli/formatters/table.py
acled/cli/utils/__init__.py
acled/cli/utils/auth.py
acled/cli/utils/config.py
acled/clients/__init__.py
acled/clients/acled_data_client.py
acled/clients/actor_client.py
acled/clients/actor_type_client.py
acled/clients/base_http_client.py
acled/clients/client.py
acled/clients/country_client.py
acled/clients/deleted_client.py
acled/clients/region_client.py
acled/models/__init__.py
acled/models/data_models.py
acled/models/enums.py
acled-0.2.4.dist-info/licenses/LICENSE.md
acled-0.2.4.dist-info/METADATA
acled-0.2.4.dist-info/WHEEL
acled-0.2.4.dist-info/entry_points.txt
acled-0.2.4.dist-info/top_level.txt
acled-0.2.4.dist-info/RECORD
