Metadata-Version: 2.4
Name: acled
Version: 0.2.4
Summary: A Python library that unofficially wraps the ACLED API.
Home-page: https://github.com/blazeiburgess/acled
Author: Blaze Burgess
Author-email: Blaze Burgess <blaze.i.burgess@gmail.com>
License: GPL 3
Project-URL: Homepage, https://github.com/blazeiburgess/acled
Project-URL: Repository, https://github.com/blazeiburgess/acled
Keywords: acled,api,conflict,data,political violence,research
Classifier: Development Status :: 4 - Beta
Classifier: Intended Audience :: Developers
Classifier: Intended Audience :: Science/Research
Classifier: License :: OSI Approved :: GNU General Public License v3 (GPLv3)
Classifier: Programming Language :: Python :: 3
Classifier: Programming Language :: Python :: 3.8
Classifier: Programming Language :: Python :: 3.9
Classifier: Programming Language :: Python :: 3.10
Classifier: Programming Language :: Python :: 3.11
Classifier: Programming Language :: Python :: 3.12
Classifier: Topic :: Scientific/Engineering :: Information Analysis
Classifier: Topic :: Software Development :: Libraries :: Python Modules
Requires-Python: >=3.8
License-File: LICENSE.md
Requires-Dist: requests>=2.26.0
Provides-Extra: dev
Requires-Dist: pytest; extra == "dev"
Requires-Dist: pylint; extra == "dev"
Requires-Dist: pytest-cov; extra == "dev"
Provides-Extra: cli
Requires-Dist: tabulate>=0.9.0; extra == "cli"
Requires-Dist: colorama>=0.4.0; extra == "cli"
Requires-Dist: cryptography>=3.0.0; extra == "cli"
Requires-Dist: keyring>=23.0.0; extra == "cli"
Provides-Extra: all
Requires-Dist: tabulate>=0.9.0; extra == "all"
Requires-Dist: colorama>=0.4.0; extra == "all"
Requires-Dist: cryptography>=3.0.0; extra == "all"
Requires-Dist: keyring>=23.0.0; extra == "all"
Requires-Dist: pytest; extra == "all"
Requires-Dist: pylint; extra == "all"
Requires-Dist: pytest-cov; extra == "all"
Dynamic: author
Dynamic: home-page
Dynamic: license-file
Dynamic: requires-python
